greptile.py
Greptile-0.9.dist-info/DESCRIPTION.rst
Greptile-0.9.dist-info/METADATA
Greptile-0.9.dist-info/RECORD
Greptile-0.9.dist-info/WHEEL
Greptile-0.9.dist-info/entry_points.txt
Greptile-0.9.dist-info/metadata.json
Greptile-0.9.dist-info/top_level.txt
