Metadata-Version: 2.0
Name: Greptile
Version: 0.9
Summary: Grep implementation with replace
Home-page: https://github.com/ncornette/greptile
Author: Nicolas Cornette
Author-email: nicolas.cornette@gmail.com
License: UNKNOWN
Platform: UNKNOWN
